hicumL2V2p4p0_internal-0.7.4.dist-info/METADATA
hicumL2V2p4p0_internal-0.7.4.dist-info/WHEEL
hl2.abi3.so
hicumL2V2p4p0_internal-0.7.4.dist-info/RECORD
