Metadata-Version: 2.1
Name: hicumL2V2p4p0_internal
Version: 0.7.4
Summary: A python package generated by VerilogAE
Author: 
